sqlalchemy_model_convert/__init__.py
sqlalchemy_model_convert/sqlalchemy_model_convert.py
sqlalchemy_model_convert-1.1.dist-info/METADATA
sqlalchemy_model_convert-1.1.dist-info/WHEEL
sqlalchemy_model_convert-1.1.dist-info/top_level.txt
sqlalchemy_model_convert-1.1.dist-info/RECORD
