Metadata-Version: 2.1
Name: sqlalchemy-model-convert
Version: 1.1
Summary: Use simple and convenient model transform dictionary module(Python3)
Home-page: https://github.com/persistty/sqlalchemy-model-convert
Author: tystudy
Author-email: UNKNOWN
License: UNKNOWN
Platform: UNKNOWN
